MANIFEST.in
README.rst
setup.py
wsgim_record.py
wsgim_record.egg-info/PKG-INFO
wsgim_record.egg-info/SOURCES.txt
wsgim_record.egg-info/dependency_links.txt
wsgim_record.egg-info/requires.txt
wsgim_record.egg-info/top_level.txt