Metadata-Version: 1.1
Name: wsgim-record
Version: 0.1.1
Summary: WSGI middleware for recording requests/responses.
Home-page: https://github.com/bninja/wsgim-record
Author: stan
Author-email: stan@hooper.com
License: BSD
Platform: any
Classifier: Environment :: Web Environment
Classifier: Intended Audience :: Developers
Classifier: License :: OSI Approved :: BSD License
Classifier: Operating System :: OS Independent
Classifier: Programming Language :: Python
Classifier: Topic :: Internet :: WWW/HTTP :: Dynamic Content
Classifier: Topic :: Software Development :: Libraries :: Python Modules
